{
  "legislative_session": "2025-2028",
  "identifier": "RCS0193",
  "title": "Para establecer una asignaci\u00f3n recurrente de cinco millones de d\u00f3lares ($5,000,000), con \ncargo al Fondo General del Tesoro Estatal del Gobierno de Puerto Rico, a partir del \nA\u00f1o Fiscal 2027-2028, para cubrir los gastos ordinarios de operaci\u00f3n y \nfuncionamiento de la Sociedad de Educaci\u00f3n y Rehabilitaci\u00f3n (SER) de Puerto Rico; \ny para otros fines relacionados.",
  "from_organization": "~{\"classification\": \"upper\"}",
  "classification": [
    "resolution"
  ],
  "subject": [],
  "abstracts": [],
  "other_titles": [],
  "other_identifiers": [
    {
      "identifier": "ocd-bill-pr-2025_2028-rcs193"
    }
  ],
  "actions": [
    {
      "description": "Radicado",
      "date": "2026-06-23T04:00:00+00:00",
      "organization_id": "~{\"classification\": \"legislature\"}",
      "classification": [
        "introduction"
      ],
      "related_entities": [],
      "_processing": {
        "log_file_created": "2026-07-13T06:06:56Z"
      }
    },
    {
      "description": "Aparece en Primera Lectura del Senado",
      "date": "2026-06-24T04:00:00+00:00",
      "organization_id": "~{\"classification\": \"upper\"}",
      "classification": [
        "reading-1"
      ],
      "related_entities": [],
      "_processing": {
        "log_file_created": "2026-07-13T06:06:56Z"
      }
    },
    {
      "description": "Referido a Comisi\u00f3n(es)",
      "date": "2026-06-24T04:00:00+00:00",
      "organization_id": "~{\"classification\": \"legislature\"}",
      "classification": [
        "referral-committee"
      ],
      "related_entities": [],
      "_processing": {
        "log_file_created": "2026-07-13T06:06:56Z"
      }
    }
  ],
  "sponsorships": [
    {
      "name": "Miembros   PNP - - Sistema \u00danico de Tr\u00e1mite Legislativo",
      "classification": "primary",
      "entity_type": "person",
      "primary": true,
      "person_id": "~{\"name\": \"Miembros   PNP - - Sistema \\u00danico de Tr\\u00e1mite Legislativo\"}",
      "organization_id": null
    },
    {
      "name": "Thomas  Rivera Schatz - Sistema \u00danico de Tr\u00e1mite Legislativo",
      "classification": "primary",
      "entity_type": "person",
      "primary": true,
      "person_id": "~{\"name\": \"Thomas  Rivera Schatz - Sistema \\u00danico de Tr\\u00e1mite Legislativo\"}",
      "organization_id": null
    }
  ],
  "related_bills": [],
  "versions": [
    {
      "note": "Radicado",
      "links": [
        {
          "url": "https://sutra.oslpr.org/SutraFilesGen/161563/rcs0193-26 (A-122).pdf",
          "media_type": "application/pdf"
        }
      ],
      "date": "2026-06-23",
      "classification": ""
    }
  ],
  "documents": [],
  "citations": [],
  "sources": [
    {
      "url": "https://sutra.oslpr.org/medidas/161563",
      "note": ""
    }
  ],
  "extras": {},
  "jurisdiction": {
    "id": "ocd-jurisdiction/country:us/territory:pr/government",
    "name": "Puerto Rico",
    "classification": "state",
    "division_id": "ocd-division/country:us/territory:pr"
  },
  "_processing": {
    "logs_latest_update": "2026-07-13T06:06:56Z",
    "text_extraction_latest_update": "2026-07-13T13:12:35.812608Z"
  }
}