{
  "legislative_session": "2025-2028",
  "identifier": "PS1284",
  "title": "Para enmendar la Ley N\u00fam. 254 de 27 de julio de 1974, seg\u00fan enmendada, y la Ley N\u00fam. \n168-2019, seg\u00fan enmendada, conocida como \u201cLey de Armas de Puerto Rico de 2020\u201d, a \nlos fines de regular el uso limitado de convicciones eliminadas del Certificado de \nAntecedentes Penales en procedimientos sensitivos autorizados por ley; y para otros fines \nrelacionados.",
  "from_organization": "~{\"classification\": \"upper\"}",
  "classification": [
    "bill"
  ],
  "subject": [],
  "abstracts": [],
  "other_titles": [],
  "other_identifiers": [
    {
      "identifier": "ocd-bill-pr-2025_2028-ps1284"
    }
  ],
  "actions": [
    {
      "description": "Radicado",
      "date": "2026-05-20T04:00:00+00:00",
      "organization_id": "~{\"classification\": \"legislature\"}",
      "classification": [
        "introduction"
      ],
      "related_entities": [],
      "_processing": {
        "log_file_created": "2026-07-13T06:06:56Z"
      }
    },
    {
      "description": "Aparece en Primera Lectura del Senado",
      "date": "2026-05-21T04:00:00+00:00",
      "organization_id": "~{\"classification\": \"upper\"}",
      "classification": [
        "reading-1"
      ],
      "related_entities": [],
      "_processing": {
        "log_file_created": "2026-07-13T06:06:56Z"
      }
    },
    {
      "description": "Referido a Comisi\u00f3n(es)",
      "date": "2026-05-21T04:00:00+00:00",
      "organization_id": "~{\"classification\": \"legislature\"}",
      "classification": [
        "referral-committee"
      ],
      "related_entities": [],
      "_processing": {
        "log_file_created": "2026-07-13T06:06:56Z"
      }
    }
  ],
  "sponsorships": [
    {
      "name": "Roxanna  I. Soto Aguil\u00fa - Sistema \u00danico de Tr\u00e1mite Legislativo",
      "classification": "primary",
      "entity_type": "person",
      "primary": true,
      "person_id": "~{\"name\": \"Roxanna  I. Soto Aguil\\u00fa - Sistema \\u00danico de Tr\\u00e1mite Legislativo\"}",
      "organization_id": null
    }
  ],
  "related_bills": [],
  "versions": [
    {
      "note": "Radicado",
      "links": [
        {
          "url": "https://sutra.oslpr.org/SutraFilesGen/161278/ps1284-26.pdf",
          "media_type": "application/pdf"
        }
      ],
      "date": "2026-05-20",
      "classification": ""
    }
  ],
  "documents": [],
  "citations": [],
  "sources": [
    {
      "url": "https://sutra.oslpr.org/medidas/161278",
      "note": ""
    }
  ],
  "extras": {},
  "jurisdiction": {
    "id": "ocd-jurisdiction/country:us/territory:pr/government",
    "name": "Puerto Rico",
    "classification": "state",
    "division_id": "ocd-division/country:us/territory:pr"
  },
  "_processing": {
    "logs_latest_update": "2026-07-13T06:06:56Z",
    "text_extraction_latest_update": "2026-07-13T10:17:07.219788Z"
  }
}